refine/__init__.py
refine/__main__.py
refine/_version.py
refine/_version.pyi
refine/abc.py
refine/cli.py
refine/config.py
refine/exc.py
refine/processor.py
refine/registry.py
refine/testing.py
refine/utils.py
refine/mods/__init__.py
refine/mods/cli/__init__.py
refine/mods/cli/flags.py
refine/mods/sql/.sqlfluff
refine/mods/sql/__init__.py
refine/mods/sql/fmt.py
refine/mods/sql/utils.py
refine-0.13.1.dist-info/METADATA
refine-0.13.1.dist-info/WHEEL
refine-0.13.1.dist-info/entry_points.txt
refine-0.13.1.dist-info/licenses/LICENSE
refine-0.13.1.dist-info/RECORD
