Metadata-Version: 2.4
Name: refine
Version: 0.13.1
Summary: Polishing and improving codebases automatically
Project-URL: Repository, https://github.com/s0undt3ch/refine
Project-URL: Documentation, https://s0undt3ch.github.io/refine
Project-URL: Issues, https://github.com/s0undt3ch/refine/issues
Project-URL: Changelog, https://github.com/s0undt3ch/refine/blob/main/CHANGELOG.md
Author-email: Pedro Algarvio <pedro@algarvio.me>
License-Expression: Apache-2.0
License-File: LICENSE
Requires-Python: <4,>3.11
Requires-Dist: libcst<1.8.0
Requires-Dist: msgspec>=0.19.0
Requires-Dist: py-walk>=0.3.3
Requires-Dist: sqlfluff<4,>=3.4
Requires-Dist: tomllib>=1.1.0; python_version < '3.11'
